si_clad/DBSCAN.py
si_clad/__init__.py
si_clad/gendata.py
si_clad/main.py
si_clad/overconditioning.py
si_clad/parametric.py
si_clad/util.py
si_clad-0.0.2.dist-info/LICENSE
si_clad-0.0.2.dist-info/METADATA
si_clad-0.0.2.dist-info/WHEEL
si_clad-0.0.2.dist-info/top_level.txt
si_clad-0.0.2.dist-info/RECORD
