Metadata-Version: 2.1
Name: si-clad
Version: 0.0.2
Summary: This package provides a Statistical Inference framework for testing the anomaly results obtained by DBSCAN algorithm.
Home-page: https://github.com/ntmphu/SI-CLAD
Author: Nguyen Thi Minh Phu
Author-email: phunguyenthiminh.hm@gmail.com
License: UNKNOWN
Platform: UNKNOWN
Classifier: Programming Language :: Python :: 3
Classifier: License :: OSI Approved :: MIT License
Classifier: Operating System :: OS Independent
License-File: LICENSE
Requires-Dist: mpmath
Requires-Dist: numpy (>=1.23.0)
Requires-Dist: scipy (>=1.4.1)
